<?xml version="1.0" encoding="UTF-8"?>
<objects serializationModel="Studio.01.10.00">
    <object class="MixerMaster" id="{083287a3-9479-4108-9512-c041197947ad}">
        <property name="name">
            <value>Master Bus</value>
        </property>
        <relationship name="effectChain">
            <destination>{5c99b88c-dee1-4176-8c66-63f7bbeee067}</destination>
        </relationship>
        <relationship name="panner">
            <destination>{6508c578-d643-4bec-8d17-56cbbfa1f881}</destination>
        </relationship>
        <relationship name="mixer">
            <destination>{6511cccb-cc7a-4d89-99ba-80c2442e1f39}</destination>
        </relationship>
    </object>
    <object class="MixerBusEffectChain" id="{5c99b88c-dee1-4176-8c66-63f7bbeee067}">
        <relationship name="effects">
            <destination>{81f23df4-aea8-446d-ac62-382e30c774cc}</destination>
        </relationship>
    </object>
    <object class="MixerBusPanner" id="{6508c578-d643-4bec-8d17-56cbbfa1f881}">
        <property name="overridingOutputFormat">
            <value>2</value>
        </property>
        <property name="outputFormatOverridden">
            <value>true</value>
        </property>
    </object>
    <object class="MixerBusFader" id="{81f23df4-aea8-446d-ac62-382e30c774cc}"/>
</objects>
