<?xml version="1.0" encoding="UTF-8"?>
<objects serializationModel="Studio.02.00.00">
	<object class="AudioFile" id="{17f9c1ce-0176-4120-93f1-8521c9ec6428}">
		<property name="assetPath">
			<value>Rain Thunder So Far_MB 06.wav</value>
		</property>
		<property name="isStreaming">
			<value>true</value>
		</property>
		<property name="frequencyInKHz">
			<value>96</value>
		</property>
		<property name="channelCount">
			<value>2</value>
		</property>
		<property name="length">
			<value>85.541333333333327</value>
		</property>
		<relationship name="masterAssetFolder">
			<destination>{7e472eb6-3c4b-4008-ae61-1443ecf36f70}</destination>
		</relationship>
	</object>
</objects>
